ptest_examples/__init__.py
ptest_examples/my_math.py
simple_piptest-0.0.5.dist-info/LICENSE
simple_piptest-0.0.5.dist-info/METADATA
simple_piptest-0.0.5.dist-info/WHEEL
simple_piptest-0.0.5.dist-info/top_level.txt
simple_piptest-0.0.5.dist-info/RECORD
