Metadata-Version: 2.1
Name: simple-piptest
Version: 0.0.5
Summary: simple example for uploading to pypi
Home-page: https://github.com/to_be_posted.github.io
Author: shzhang
Author-email: zhangshunhong.pku@gmail.com
Classifier: Programming Language :: Python :: 3
Classifier: License :: OSI Approved :: MIT License
Classifier: Operating System :: OS Independent
License-File: LICENSE
